dk_prod/FeatureBuilding.py
dk_prod/__init__.py
dk_prod/optimize.py
dk_prod/player.py
dk_prod/prod_utils.py
scrape_foos/__init__.py
scrape_foos/bbrefToGBQ.py
scrape_foos/playerinfo_utils.py
scrape_foos/utils.py
training/__init__.py
training/train_model.py
training/training_utils.py
ScarletNBA-0.0.3.dist-info/METADATA
ScarletNBA-0.0.3.dist-info/WHEEL
ScarletNBA-0.0.3.dist-info/top_level.txt
ScarletNBA-0.0.3.dist-info/RECORD
