Metadata-Version: 2.1
Name: ScarletNBA
Version: 0.0.3
Summary: A small NBA prediction package
Home-page: https://github.com/meirelon/NBA-NHL
Author: Michael Nestel
Author-email: nestelm@gmail.com
License: UNKNOWN
Platform: UNKNOWN
Classifier: Programming Language :: Python :: 3
Classifier: License :: OSI Approved :: MIT License
Classifier: Operating System :: OS Independent
